aliyunsdkimarketing/__init__.py
aliyunsdkimarketing/request/__init__.py
aliyunsdkimarketing/request/v20220704/CreateDeviceRequest.py
aliyunsdkimarketing/request/v20220704/GetBrandPageRequest.py
aliyunsdkimarketing/request/v20220704/GetMainPartPageRequest.py
aliyunsdkimarketing/request/v20220704/GetUserFinishedAdRequest.py
aliyunsdkimarketing/request/v20220704/ListAdvertisingRequest.py
aliyunsdkimarketing/request/v20220704/SendSmsRequest.py
aliyunsdkimarketing/request/v20220704/__init__.py
aliyun_python_sdk_imarketing-5.0.2.dist-info/LICENSE
aliyun_python_sdk_imarketing-5.0.2.dist-info/METADATA
aliyun_python_sdk_imarketing-5.0.2.dist-info/WHEEL
aliyun_python_sdk_imarketing-5.0.2.dist-info/top_level.txt
aliyun_python_sdk_imarketing-5.0.2.dist-info/RECORD
